MANIFEST.in
README.md
setup.cfg
setup.py
versioneer.py
brilleu/__init__.py
brilleu/_version.py
brilleu/brilleu.py
brilleu/castep.py
brilleu/crystal.py
brilleu/timeit.py
brilleu/utilities.py
brilleu.egg-info/PKG-INFO
brilleu.egg-info/SOURCES.txt
brilleu.egg-info/dependency_links.txt
brilleu.egg-info/requires.txt
brilleu.egg-info/top_level.txt