Metadata-Version: 2.1
Name: brilleu
Version: 0.2.3
Summary: an interface between brille and Euphonic
Home-page: https://github.com/brille/brilleu
Author: Greg Tucker
Author-email: greg.tucker@stfc.ac.uk
License: UNKNOWN
Platform: UNKNOWN
Classifier: Development Status :: 3 - Alpha
Classifier: Programming Language :: Python :: 3
Classifier: License :: OSI Approved :: GNU General Public License v3 or later (GPLv3+)
Classifier: Operating System :: OS Independent
Classifier: Topic :: Scientific/Engineering
Requires-Python: ~=3.6
